{
  "descriptionHash": "AB347B6D4682EEC5ACCFCAD72F14AFF8E65F5CC63566528EAA70FC23D007BA4384DA615BC90D44CE05112B709548F1B72D6F9D52366B924E65C2D0914FA75946",
  "descriptionLocation": "../../openapi.fixed.json",
  "lockFileVersion": "1.0.0",
  "kiotaVersion": "1.31.1",
  "clientClassName": "OpenHandsOpenApiClient",
  "typeAccessModifier": "Public",
  "clientNamespaceName": "Soenneker.OpenHands.OpenApiClient",
  "language": "CSharp",
  "usesBackingStore": false,
  "excludeBackwardCompatible": true,
  "includeAdditionalData": true,
  "disableSSLValidation": false,
  "serializers": [
    "Microsoft.Kiota.Serialization.Json.JsonSerializationWriterFactory",
    "Microsoft.Kiota.Serialization.Text.TextSerializationWriterFactory",
    "Microsoft.Kiota.Serialization.Form.FormSerializationWriterFactory",
    "Microsoft.Kiota.Serialization.Multipart.MultipartSerializationWriterFactory"
  ],
  "deserializers": [
    "Microsoft.Kiota.Serialization.Json.JsonParseNodeFactory",
    "Microsoft.Kiota.Serialization.Text.TextParseNodeFactory",
    "Microsoft.Kiota.Serialization.Form.FormParseNodeFactory"
  ],
  "structuredMimeTypes": [
    "application/json",
    "text/plain;q=0.9",
    "application/x-www-form-urlencoded;q=0.2",
    "multipart/form-data;q=0.1"
  ],
  "includePatterns": [],
  "excludePatterns": [],
  "disabledValidationRules": []
}